voltagent/__init__.py
voltagent/client.py
voltagent/sdk.py
voltagent/types.py
voltagent-0.1.1.dist-info/licenses/LICENSE
voltagent-0.1.1.dist-info/METADATA
voltagent-0.1.1.dist-info/WHEEL
voltagent-0.1.1.dist-info/top_level.txt
voltagent-0.1.1.dist-info/RECORD
